certbot_bigip/__init__.py
certbot_bigip/configurator.py
certbot_bigip/constants.py
certbot_bigip/obj.py
tests/__init__.py
tests/test_bigip_configurator.py
tests/test_shellcommands.py
certbot_bigip-1.2.1.dist-info/METADATA
certbot_bigip-1.2.1.dist-info/WHEEL
certbot_bigip-1.2.1.dist-info/entry_points.txt
certbot_bigip-1.2.1.dist-info/top_level.txt
certbot_bigip-1.2.1.dist-info/RECORD
