Metadata-Version: 2.1
Name: certbot-bigip
Version: 1.2.1
Summary: F5 BIG-IP plugin for Certbot
Author: Certbot Team @ Open Networks
Author-email: certbot@on.at
License: Apache License 2.0
Classifier: Development Status :: 4 - Beta
Classifier: Environment :: Plugins
Classifier: Intended Audience :: System Administrators
Classifier: License :: OSI Approved :: Apache Software License
Classifier: Operating System :: POSIX :: Linux
Classifier: Programming Language :: Python
Classifier: Programming Language :: Python :: 3
Classifier: Programming Language :: Python :: 3.7
Classifier: Programming Language :: Python :: 3.8
Classifier: Programming Language :: Python :: 3.9
Classifier: Programming Language :: Python :: 3.10
Classifier: Programming Language :: Python :: 3.11
Classifier: Topic :: Internet :: WWW/HTTP
Classifier: Topic :: Security
Classifier: Topic :: System :: Installation/Setup
Classifier: Topic :: System :: Networking
Classifier: Topic :: System :: Systems Administration
Classifier: Topic :: Utilities
Requires-Python: >=3.7
Requires-Dist: acme
Requires-Dist: certbot
Requires-Dist: f5-icontrol-rest
Requires-Dist: f5-sdk
Requires-Dist: requests
Requires-Dist: setuptools (>=1.0)
